poetry_demo_alex_vamvakaris/__init__.py
poetry_demo_alex_vamvakaris/hello.py
poetry_demo_alex_vamvakaris-0.2.0.dist-info/METADATA
poetry_demo_alex_vamvakaris-0.2.0.dist-info/WHEEL
poetry_demo_alex_vamvakaris-0.2.0.dist-info/RECORD
